{
  "_readme": "Run npm run sounds:import to copy into {id}.mp3",
  "cow": "animal sounds/a_cow_mooing_#3-1780191773686.mp3",
  "duck": "animal sounds/a_duck_quacking_#1-1780191744083.mp3",
  "golden_retriever": "animal sounds/a_golden_retriever_b_#1-1780191794453.mp3",
  "lion": "animal sounds/a_lion_roaring_loud_#2-1780191843914.mp3",
  "turkey": "animal sounds/a_turkey_gobbling_#3-1780191879302.mp3",
  "eagle": "animal sounds/a_bald_eagle_hunting_#1-1780192071847.mp3",
  "cockatiel": "animal sounds/a_cockateil_chirping_#1-1780192176735.mp3",
  "blue_jay": "animal sounds/a_bluejay_chirping_#1-1780192209926.mp3",
  "cardinal": "animal sounds/a_cardinal_chirping_#1-1780192221634.mp3",
  "pelican": "animal sounds/a_pelican_making_pel_#4-1780192252287.mp3",
  "albatross": "animal sounds/an_albatross_chirpin_#1-1780192279896.mp3",
  "barn_owl": "animal sounds/a_barn_owl_whooing_#2-1780192331236.mp3",
  "toucan": "animal sounds/a_toucan_making_touc_#1-1780192490122.mp3",
  "macaw": "animal sounds/a_macaw_cawing_and_t_#4-1780192433935.mp3",
  "elephant": "animal sounds/an_african_elephants_#1-1780192517304.mp3",
  "hyena": "animal sounds/a_hyena_laughing_#2-1780192545513.mp3",
  "polar_bear": "animal sounds/a_polarbear_roaring_#1-1780192577704.mp3",
  "arctic_fox": "animal sounds/artic_fox_making_noi_#2-1780192598901.mp3",
  "arctic_hare": "animal sounds/artic_hare_making_no_#1-1780192621592.mp3",
  "arctic_wolf": "animal sounds/artic_wolf_howling_#1-1780192635742.mp3",
  "caribou": "animal sounds/Caribou_bellowing_wi_#1-1780192654751.mp3",
  "_unused_asian_elephant": "animal sounds/an_asian_elephants_w_#1-1780192527851.mp3"
}
